crazy_thursday/__init__.py
crazy_thursday/__main__.py
crazy_thursday/corpus.jsonl
crazy_thursday/requirements.txt
scripts/__init__.py
scripts/get_issues.py
scripts/update_curpus.py
crazy_thursday-2025.1.11.0.dist-info/LICENSE
crazy_thursday-2025.1.11.0.dist-info/METADATA
crazy_thursday-2025.1.11.0.dist-info/WHEEL
crazy_thursday-2025.1.11.0.dist-info/entry_points.txt
crazy_thursday-2025.1.11.0.dist-info/top_level.txt
crazy_thursday-2025.1.11.0.dist-info/RECORD
