Metadata-Version: 2.1
Name: crazy-thursday
Version: 2025.1.11.0
Summary: a cli tool to print crazy thursday article
Home-page: https://github.com/zqmillet/sphinx-console
Author: kinopico
Author-email: zqmillet@qq.com
License-File: LICENSE
Requires-Dist: rich ==12.5.1
